LICENSE
MANIFEST.in
NOTICE
README.rst
setup.py
examples/eventlet_longpoll.py
examples/eventlet_test.py
examples/gevent_longpoll.py
examples/gevent_websocket.py
examples/grainbows.conf.py
examples/grainbows.conf.py.sample
examples/test_keepalive.py
examples/test_keepalive.pyc
examples/websocket.html
examples/websocket.py
grainbows/__init__.py
grainbows/config.py
grainbows/eventlet_server.py
grainbows/gevent_server.py
grainbows/http_request.py
grainbows/http_response.py
grainbows/main.py
grainbows/worker_base.py
grainbows.egg-info/PKG-INFO
grainbows.egg-info/SOURCES.txt
grainbows.egg-info/dependency_links.txt
grainbows.egg-info/entry_points.txt
grainbows.egg-info/not-zip-safe
grainbows.egg-info/requires.txt
grainbows.egg-info/top_level.txt